kagglehub/__init__.py
kagglehub/auth.py
kagglehub/cache.py
kagglehub/clients.py
kagglehub/colab_cache_resolver.py
kagglehub/competition.py
kagglehub/config.py
kagglehub/datasets.py
kagglehub/datasets_enums.py
kagglehub/datasets_helpers.py
kagglehub/enum.py
kagglehub/env.py
kagglehub/exceptions.py
kagglehub/gcs_upload.py
kagglehub/handle.py
kagglehub/hf_datasets.py
kagglehub/http_resolver.py
kagglehub/integrity.py
kagglehub/kaggle_cache_resolver.py
kagglehub/logger.py
kagglehub/models.py
kagglehub/models_helpers.py
kagglehub/notebooks.py
kagglehub/packages.py
kagglehub/pandas_datasets.py
kagglehub/polars_datasets.py
kagglehub/registry.py
kagglehub/resolver.py
kagglehub/signing.py
kagglehub/tracker.py
kagglehub/utility_scripts.py
kagglehub-0.4.1.dist-info/METADATA
kagglehub-0.4.1.dist-info/WHEEL
kagglehub-0.4.1.dist-info/licenses/LICENSE
kagglehub-0.4.1.dist-info/RECORD
