Metadata-Version: 2.3
Name: kagglehub
Version: 0.4.1
Summary: Access Kaggle resources anywhere
Project-URL: Homepage, https://github.com/Kaggle/kagglehub
Project-URL: Bug Tracker, https://github.com/Kaggle/kagglehub/issues
Author-email: Kaggle <support@kaggle.com>
License:                                  Apache License
Keywords: API,Kaggle
Classifier: License :: OSI Approved :: Apache Software License
Classifier: Operating System :: OS Independent
Classifier: Programming Language :: Python :: 3
Requires-Python: >=3.10
Requires-Dist: kagglesdk<1.0,>=0.1.14
Requires-Dist: packaging
Requires-Dist: pyyaml
Requires-Dist: requests
Requires-Dist: tqdm
Provides-Extra: hf-datasets
Requires-Dist: datasets; extra == 'hf-datasets'
Requires-Dist: pandas; extra == 'hf-datasets'
Provides-Extra: pandas-datasets
Requires-Dist: pandas; extra == 'pandas-datasets'
Provides-Extra: polars-datasets
Requires-Dist: polars; extra == 'polars-datasets'
Provides-Extra: signing
Requires-Dist: betterproto>=2.0.0b6; extra == 'signing'
Requires-Dist: model-signing; extra == 'signing'
Requires-Dist: sigstore>=3.6.1; extra == 'signing'
